jones_complexity.py
jones_complexity-0.1.2.dist-info/DESCRIPTION.rst
jones_complexity-0.1.2.dist-info/entry_points.txt
jones_complexity-0.1.2.dist-info/METADATA
jones_complexity-0.1.2.dist-info/metadata.json
jones_complexity-0.1.2.dist-info/RECORD
jones_complexity-0.1.2.dist-info/top_level.txt
jones_complexity-0.1.2.dist-info/WHEEL
